ndicom_kmeans/__init__.py
ndicom_kmeans/plugin.py
ndicom_kmeans-0.0.1.dev0.dist-info/METADATA
ndicom_kmeans-0.0.1.dev0.dist-info/RECORD
ndicom_kmeans-0.0.1.dev0.dist-info/WHEEL
ndicom_kmeans-0.0.1.dev0.dist-info/dependency_links.txt
ndicom_kmeans-0.0.1.dev0.dist-info/top_level.txt
